brighter/__init__.py
brighter/airflow/__init__.py
brighter/airflow/alerts/__init__.py
brighter/airflow/alerts/slack.py
brighter/airflow/operators/__init__.py
brighter/airflow/operators/bigquery.py
brighter/api/__init__.py
brighter/api/core.py
brighter/collections.py
brighter/gcp/__init__.py
brighter/gcp/bigquery.py
brighter/gcp/credentials.py
brighter/gcp/storage.py
brighter-0.1.1.dist-info/LICENSE
brighter-0.1.1.dist-info/METADATA
brighter-0.1.1.dist-info/WHEEL
brighter-0.1.1.dist-info/RECORD
