Metadata-Version: 2.1
Name: brighter
Version: 0.1.1
Summary: A simple library for data-wrangling with GCP support
License: MIT
Requires-Python: >=3.11,<3.12
Classifier: License :: OSI Approved :: MIT License
Classifier: Programming Language :: Python :: 3
Classifier: Programming Language :: Python :: 3.11
Requires-Dist: apache-airflow (>=2.6.2,<3.0.0)
Requires-Dist: apache-airflow-providers-google (>=10.3.0,<11.0.0)
Requires-Dist: apache-airflow-providers-http (>=4.4.2,<5.0.0)
Requires-Dist: apache-airflow-providers-slack[http] (>=7.3.1,<8.0.0)
Requires-Dist: pandas (>=2.0.3,<3.0.0)
Requires-Dist: pandas-gbq (>=0.19.2,<0.20.0)
